odoo/addons/l10n_jp_account_report_registration_number/README.rst
odoo/addons/l10n_jp_account_report_registration_number/__init__.py
odoo/addons/l10n_jp_account_report_registration_number/__manifest__.py
odoo/addons/l10n_jp_account_report_registration_number/i18n/ja.po
odoo/addons/l10n_jp_account_report_registration_number/i18n/l10n_jp_account_report_registration_number.pot
odoo/addons/l10n_jp_account_report_registration_number/models/__init__.py
odoo/addons/l10n_jp_account_report_registration_number/models/account_move.py
odoo/addons/l10n_jp_account_report_registration_number/models/account_payment.py
odoo/addons/l10n_jp_account_report_registration_number/models/registration_number_mixin.py
odoo/addons/l10n_jp_account_report_registration_number/readme/DESCRIPTION.rst
odoo/addons/l10n_jp_account_report_registration_number/static/description/icon.png
odoo/addons/l10n_jp_account_report_registration_number/static/description/index.html
odoo/addons/l10n_jp_account_report_registration_number/tests/__init__.py
odoo/addons/l10n_jp_account_report_registration_number/tests/test_account_report_registration_number.py
odoo/addons/l10n_jp_account_report_registration_number/views/report_templates.xml
odoo_addon_l10n_jp_account_report_registration_number-16.0.1.0.0.4.dist-info/METADATA
odoo_addon_l10n_jp_account_report_registration_number-16.0.1.0.0.4.dist-info/WHEEL
odoo_addon_l10n_jp_account_report_registration_number-16.0.1.0.0.4.dist-info/top_level.txt
odoo_addon_l10n_jp_account_report_registration_number-16.0.1.0.0.4.dist-info/RECORD
