Metadata-Version: 2.1
Name: odoo-addon-l10n-jp-account-report-registration-number
Version: 16.0.1.0.0.4
Summary: Japan Account Report Registration Number
Home-page: https://github.com/OCA/l10n-japan
Author: Quartile Limited, Odoo Community Association (OCA)
Author-email: support@odoo-community.org
License: AGPL-3
Platform: UNKNOWN
Classifier: Programming Language :: Python
Classifier: Framework :: Odoo
Classifier: Framework :: Odoo :: 16.0
Classifier: License :: OSI Approved :: GNU Affero General Public License v3
Requires-Python: >=3.10
Requires-Dist: odoo <16.1dev,>=16.0a
